{
    "code":0,
    "msg":"操作成功",
    "data":{
        "id":"1",
        "sale_force":"0",
        "vip_share_text":"邀请你成为vip会员",
        "vip_share_img":"http://file.dev.xinduobang.cn/headimg/6414e5a2a310f8419abbb9da8d8b930c.jpeg",
        "store_id":"1",
        "is_spend_bai":"0",
        "is_course_list":"0",
        "is_course_details":"0",
        "spend_bai_money":"1000.00",
        "auto_harvest":"0",
        "harvest_day":"0",
        "is_check_address":"1",
        "full_freight":"1",
        "money_pay":"1",
        "money_pay_price":"100.01",
        "coin_pay":"1",
        "coin_pay_num":"10",
        "sys_default":"1",
        "sys_limit":"1",
        "is_share_product":"2",
        "is_comment":"0",
        "dj_type":"1",
        "is_reply":"0",
        "is_to_comment":"1",
        "is_look":"1",
        "is_pic_verify":"0",
        "is_line_up":"1",
        "part_time_guide":"<p style="text-align: center;font-size:18px;"><strong>申请加入兼职导师</strong></p >",
        "webtitle":"信多帮",
        "logo":"http://file.dev.xinduobang.cn/2021-11-18/61960edc3522a.png",
        "loginlogo":"http://file.dev.xinduobang.cn/2018-09-13/5b9a1207d060c.png",
        "loginbanner":"http://file.dev.xinduobang.cn/2021-11-18/6196230647ac3.png",
        "wxname":"信多帮",
        "wxcode":"http://file.dev.xinduobang.cn/2018-05-09/5af2a572295c7.jpg",
        "is_points":"0",
        "changepoint":"0.00",
        "salenum_show":"0",
        "is_vip":"1",
        "timelimit":"150",
        "temptimelimit":"150",
        "shop_status":"1",
        "bank_account":"0",
        "refund_status":"0",
        "wxkf_status":"1",
        "invite_other_coin":"6",
        "invite_other_status":"0",
        "invite_status":"1",
        "invite_coin":"20",
        "invite_rule":"百度首页
    年轻的我们day
    消息
    商城

网页 新闻 贴吧 知道 音乐 图片 视频 地图 文库 百科
帮助
声明：百科词条人人可编辑，词条创建和修改均免费，绝不存在官方及代理商付费代编，请勿上当受骗。详情>>",
        "ice_rule":"冻结状态的虚拟币会在被邀请人结营时清算转换为可用状态，如果被邀请人退营，则会扣除对应奖励",
        "ice_type":"0",
        "ice_day":"0",
        "invited_money":"0.01",
        "phone_status":"2",
        "photo_default":"0",
        "photo_json":"{"position_type":1,"position":"9","imgurl":"http://file.dev.xinduobang.cn/headimg/b0de8d2b285ba5b98b37a25344766f45.png","font":"","size":"","color":"","watersize":"1.6"}",
        "photo_set_type":"2",
        "pic_share_text":"点击观看更多照片",
        "pic_share_url":"http://file.dev.xinduobang.cn/headimg/46841f0562a664fc151746043dfa933f.jpeg",
        "dongtai_status":"1",
        "auto_band":"1",
        "shoprefund_status":"0",
        "video_thumb":"http://file.dev.xinduobang.cn/headimg/cb4ab10040e8333b6664525ff6a054b4.jpeg",
        "invite_pic":"http://file.dev.xinduobang.cn/headimg/7ab875911263d895800289f7390a38da.jpeg",
        "sms_status":"1",
        "dingjin":"1",
        "is_step_order":"1",
        "czk_status":"1",
        "is_lastprice":"1",
        "cate_json":"{"borderStyle":"#cccccc","borderStyleShadow":"#1c4587","borderStyleShadowArg1":"20","borderStyleShadowArg2":"5","backgroundColor":"#ffffff","shadowFlag":"0","borderFlag":"1","selectBackgroundColor":"#ffffff","list":[{"pagePath":"/pages/index/index","key":"首页","linkType":8,"text":"首页","iconPath":"http://test.cdn.xinduobang.cn/url/pagediy/202902113128273051.png","selectedIconPath":"http://test.cdn.xinduobang.cn/url/pagediy/202902113131749315.png","color":"#999999","selectedColor":"#6aa84f","borderStyleShadowArg1":"3","borderStyleShadowArg2":"3","shadowFlag":"0"},{"pagePath":"/pages/camp/camp?type_id=0","key":"产品列表","link":"0","linkType":0,"text":"户外营地","iconPath":"http://test.cdn.xinduobang.cn/url/pagediy/202902113116423553.png","selectedIconPath":"http://test.cdn.xinduobang.cn/url/pagediy/202902113120610080.png","color":"#999999","selectedColor":"#6aa84f"},{"pagePath":"/pages/dynamic/dynamic","key":"动态","link":"/pages/dynamic/dynamic","linkType":2,"text":"动态","iconPath":"https://file.dev.xinduobang.cn/tabbar/dongtai.png","selectedIconPath":"https://file.dev.xinduobang.cn/tabbar/dongtaied.png","color":"#999","selectedColor":"#44af69"},{"pagePath":"/pages/shop/shop","key":"商城","link":"/pages/shop/shop","linkType":6,"text":"商城","iconPath":"https://file.dev.xinduobang.cn/tabbar/shop.png","selectedIconPath":"https://file.dev.xinduobang.cn/tabbar/shopon.png","ck":false,"color":"#999","selectedColor":"#44af69"},{"pagePath":"/pages/user/user","key":"个人中心","text":"我的","iconPath":"http://test.cdn.xinduobang.cn/url/pagediy/202902113134785586.png","selectedIconPath":"http://test.cdn.xinduobang.cn/url/pagediy/202902113136892233.png","ck":false,"color":"#999999","selectedColor":"#44af69","linkType":7,"shadowFlag":"0","selectBackgroundColor":"#d3e3fc"}],"switch_city":"1"}",
        "vip_name":"会员VIP",
        "vip_num":"0",
        "vip_type_status":"0",
        "is_step_user":"1",
        "is_step_vipcard":"1",
        "message_status":"0",
        "index_content":"{"status":"1","music":"0","skip":"1","musicName":"","skipTime":"30","bgimg":"http://file.dev.xinduobang.cn/headimg/4a694088d2dd25498b66e93b19aa821e.jpeg","mode":"aspectFill","linkName":"首页","linkPath":"/pages/index/index","bgcolor":"#000000","musicUrl":""}",
        "is_step_icard":"1",
        "is_renzheng":"1",
        "is_change":"0",
        "email_content":"合同已发至您邮箱，请您点击链接下载{esign_url}",
        "send_coupon_status":"0",
        "card_id":"",
        "rz_open":"0",
        "moneyfund_status":"1",
        "invite_coin_year":"0",
        "ice_type_year":"0",
        "ice_day_year":"0",
        "invited_money_year":"0.00",
        "invite_by_type_year":"2",
        "invite_to_type_year":"1",
        "invite_to_product_year":"""",
        "invite_by_product_year":"""",
        "invite_radio_year":"2",
        "invite_discount_year":"50",
        "invite_by_radio_year":"2",
        "invite_by_discount_year":"5.00",
        "staff_band":"1",
        "custom_order":"1",
        "service_time":"上午9点到下午18点",
        "is_show_card":"1",
        "invite_by_type":"1",
        "invite_to_type":"1",
        "invite_to_product":"[{"goods_icon":"2","coin":"","percentcoin":"10","pids":["946"]},{"goods_icon":"1","coin":"1","percentcoin":"","pids":["1148"]}]",
        "invite_by_product":"""",
        "backperio":"0",
        "backperio_num":"0",
        "backperio_day":"0",
        "is_auto_group":"1",
        "auto_group_type":"1",
        "kol_connect":"2",
        "invite_radio":"1",
        "invite_discount":"0.0",
        "invite_by_radio":"1",
        "invite_by_discount":"0.0",
        "is_auto_grade":"1",
        "channel_connect":"0",
        "role_derate":"1",
        "login_backimg":"http://file.dev.xinduobang.cn/headimg/88dbb1b737783a3090ae2444a0a533ce.png",
        "sale_limit":"1",
        "sale_time":"0",
        "ask_text":"客服",
        "ask_icon":"http://file.dev.xinduobang.cn/2021-12-13/61b7103f369e9.jpg",
        "online_ask":"在线咨询",
        "wein_ask":"微信群咨询",
        "messageturn":"1",
        "signoff_qotername":"您好，请确认营期消息并签出",
        "signoff_qotercolor":"#ff0000",
        "signoffbg_img":"http://test.cdn.xinduobang.cn/headimg/3ffe551f29ae7fcff48df763e698c3c9.png",
        "signoff_img":"http://file.dev.xinduobang.cn/headimg/0f1defa9e0c1b8040bd1cbdb398f5cd0.png",
        "signoffsuccess_img":"http://file.dev.xinduobang.cn/headimg/6a8a91d080da0033879bccaea1cca249.png",
        "sign_qotername":"您好，请确认参会信息并签到",
        "sign_qotercolor":"#0000ff",
        "signbg_img":"http://test.cdn.xinduobang.cn/headimg/3ffe551f29ae7fcff48df763e698c3c9.png",
        "sign_img":"http://test.cdn.xinduobang.cn/headimg/dc51a72bb00dd5b76c05eb60ef0478ab.png",
        "signsuccess_img":"http://file.dev.xinduobang.cn/headimg/e1639a319c7386aaad581c334c6b60fd.png",
        "signoff_finishimg":"http://file.dev.xinduobang.cn/headimg/0222eb9a37ef4e086f390cca0f8d845e.jpeg",
        "signfinish_img":"http://file.dev.xinduobang.cn/headimg/81d1b159d6a1cbca19716a2f95271474.jpeg",
        "contruct_success_msg":"111111111111",
        "must_contract":"0",
        "sign_type":"0",
        "refund_rule":"提交后，请联系您的专属客服！手机号：18810416068    提交后，请联系您的专属客服！手机号：18810416068",
        "photo_type":"["1","2","3","4"]",
        "photo_type_default":"1",
        "share_type":"["2","3"]",
        "share_type_default":"3",
        "share_poster":"http://file.dev.xinduobang.cn/headimg/da4fc3b97793c2153f628baa65b78ae4.jpeg",
        "share_poster_position":"{"height":"667","x":"139","y":"476"}",
        "dk_is_card":"1",
        "dk_is_moneycard":"1",
        "dk_is_coin":"1",
        "dk_band":"1",
        "dk_share_text":"点此链接，立即报名",
        "cut_num_type":"2",
        "cut_num":"32132",
        "cut_share_title":"发现好的活动，快来加入吧！哈哈哈",
        "cut_share_desc":"",
        "cut_share_img":"http://file.dev.xinduobang.cn/headimg/5e1260cbb3b6d541db6d2f28c4dc8be3.jpeg",
        "cut_share_poster":"http://file.dev.xinduobang.cn/headimg/1a41b33f18ef4da4030d98d661f7cde1.jpeg",
        "cut_share_x":"291",
        "cut_share_y":"503",
        "cut_btn_desc":"1砍价",
        "cut_img_size":"83",
        "vip_tq_type":"1",
        "vip_givecoin":"0.0",
        "vip_coursestr":"",
        "sign_pic_status":"2",
        "sign_pic_status1":"1",
        "loginbanner1":"http://file.dev.xinduobang.cn/2021-11-18/6196230647ac3.png",
        "is_sc":"0",
        "is_coinrank":"1",
        "ty_open":"1",
        "hy_open":"2",
        "cshare_type":"2",
        "cshare":"哒哒哒哒哒哒多多多多56565656",
        "fshare_type":"2",
        "fshare":"赶快加入吧！",
        "viptypeturn":"0",
        "switch_city":"1",
        "firstaskstatus":"1",
        "firstaskshow":"2",
        "firstaskicon":"http://file.dev.xinduobang.cn/2021-04-21/607f8c110d788.png",
        "addappid":"1",
        "cshareimg_type":"2",
        "cshareimg":"http://file.dev.xinduobang.cn/2021-11-18/6195fbdad1b26.png",
        "is_username":"2",
        "rank_status":"1",
        "rank_time":"08:54",
        "rank_cash_types":"1,2,3,4",
        "rank_invite_types":"1,2,3,4,5",
        "rank_num_types":"1,2,3,4,5",
        "rank_cash_default":"1",
        "rank_invite_default":"2",
        "rank_num_default":"3",
        "rank_msg_status":"0",
        "rank_msg_type":"0",
        "rank_msg_json":"["\u7a3d\u9996","\u6708\u53f0","\u68bc\u674c","\u795e\u6728","\u516d\u5408","\u540c\u5fc3","\u80e7\u6708"]",
        "rank_cash_order":"1",
        "rank_invite_order":"2",
        "rank_num_order":"3",
        "staff_msg_status":"1",
        "staff_msg_configs":"[{"id":1,"is_select":1},{"id":2,"is_select":1},{"id":3,"is_select":1},{"id":4,"is_select":1}]",
        "is_sale_photo":"1",
        "sale_photo_json":"[]",
        "sale_login":"0",
        "sale_login_button":"",
        "sale_login_bg":"",
        "is_show_postprice":"2",
        "handle_time":"1",
        "shop_share_x":"0",
        "shop_share_y":"0",
        "shop_img_size":"120",
        "shop_bg_img":"http://file.dev.xinduobang.cn/headimg/6372d69c48d38e8f60a65abda7ec0325.jpeg",
        "shop_shareimg_status":"1",
        "fx_connect":"2",
        "ower_limit":"1",
        "monthbefore":[

        ],
        "monthafter":[

        ],
        "student_birthday_onoff":"1",
        "student_birthday_day":"7",
        "student_birthday_time":"15:24:00",
        "lifecomment":"生活评价哈哈",
        "coursecomment":"课程评价uu",
        "comment_check":"1",
        "student_age_start":"1",
        "student_age_end":"10",
        "user_bcimg":"http://file.dev.xinduobang.cn/headimg/44bad565befa6f4326a15c231802f896.png",
        "certificate":"1",
        "certificate_title":"123",
        "circusee_status":"1",
        "exchange":"1",
        "kfstr":[
            {
                "khdhlistname":"客服哈哈哈",
                "khdhliststr":"15911104543"
            }
        ],
        "msg_users":"18810416068",
        "is_show_ali":1,
        "login_status":"1",
        "name":"",
        "is_new":0,
        "is_same_phone":"2",
        "overflow_order_status":"1",
        "refund_time_type":0,
        "backperio_type":0,
        "index_share_status":"2",
        "index_share_text":"吧吧吧吧吧吧v333",
        "index_share_url":"http://file.dev.xinduobang.cn/headimg/db963002a685eb3ad2b37d70db663f93.jpeg",
        "service_link":"",
        "user_header_text_color":"#00ccff",
        "new_refund_status":0,
        "new_refund_time_type":0,
        "new_refund_day":0,
        "new_exchange_status":0,
        "new_exchange_time_type":0,
        "new_exchange_day":0,
        "new_refund_service_charge":0,
        "together_people_status":"1",
        "together_people_copywriting":"扣扣扣扣扣",
        "together_people_img":"",
        "is_card_status":0,
        "is_student_module":"1",
        "big_status":"1",
        "small_status":"1",
        "big_form_id":"238",
        "small_form_id":"246",
        "support_camp_change":0,
        "is_qywx":0
    }
}